{
  "matches": [
    {
      "part": "1.jpg",
      "image": "picsum.photos0.jpg",
      "x": 32,
      "y": 88
    },
    {
      "part": "2.jpg",
      "image": "picsum.photos1.jpg",
      "x": 128,
      "y": 140
    },
    {
      "part": "3.jpg",
      "image": "picsum.photos2.jpg",
      "x": 48,
      "y": 152
    },
    {
      "part": "4.jpg",
      "image": "picsum.photos3.jpg",
      "x": 84,
      "y": 100
    },
    {
      "part": "5.jpg",
      "image": "picsum.photos4.jpg",
      "x": 144,
      "y": 8
    },
    {
      "part": "6.jpg",
      "image": "picsum.photos7.jpg",
      "x": 164,
      "y": 120
    },
    {
      "part": "7.jpg",
      "image": "picsum.photos8.jpg",
      "x": 148,
      "y": 192
    },
    {
      "part": "8.jpg",
      "image": "picsum.photos8.jpg",
      "x": 140,
      "y": 56
    },
    {
      "part": "9.jpg",
      "image": "picsum.photos9.jpg",
      "x": 120,
      "y": 24
    },
    {
      "part": "10.jpg",
      "image": "picsum.photos10.jpg",
      "x": 184,
      "y": 132
    },
    {
      "part": "11.jpg",
      "image": "picsum.photos12.jpg",
      "x": 163,
      "y": 216
    },
    {
      "part": "12.jpg",
      "image": "picsum.photos13.jpg",
      "x": 152,
      "y": 24
    },
    {
      "part": "13.jpg",
      "image": "picsum.photos15.jpg",
      "x": 92,
      "y": 96
    },
    {
      "part": "14.jpg",
      "image": "picsum.photos16.jpg",
      "x": 76,
      "y": 140
    },
    {
      "part": "15.jpg",
      "image": "picsum.photos17.jpg",
      "x": 32,
      "y": 88
    },
    {
      "part": "16.jpg",
      "image": "picsum.photos18.jpg",
      "x": 9,
      "y": 169
    },
    {
      "part": "17.jpg",
      "image": "picsum.photos19.jpg",
      "x": 48,
      "y": 56
    },
    {
      "part": "18.jpg",
      "image": "picsum.photos22.jpg",
      "x": 0,
      "y": 168
    },
    {
      "part": "19.jpg",
      "image": "picsum.photos23.jpg",
      "x": 144,
      "y": 108
    },
    {
      "part": "20.jpg",
      "image": "picsum.photos24.jpg",
      "x": 156,
      "y": 60
    },
    {
      "part": "21.jpg",
      "image": "picsum.photos25.jpg",
      "x": 160,
      "y": 116
    },
    {
      "part": "22.jpg",
      "image": "picsum.photos26.jpg",
      "x": 24,
      "y": 128
    },
    {
      "part": "23.jpg",
      "image": "picsum.photos27.jpg",
      "x": 124,
      "y": 164
    },
    {
      "part": "24.jpg",
      "image": "picsum.photos28.jpg",
      "x": 88,
      "y": 20
    },
    {
      "part": "25.jpg",
      "image": "picsum.photos29.jpg",
      "x": 32,
      "y": 156
    },
    {
      "part": "26.jpg",
      "image": "picsum.photos30.jpg",
      "x": 100,
      "y": 180
    },
    {
      "part": "27.jpg",
      "image": "picsum.photos31.jpg",
      "x": 136,
      "y": 0
    },
    {
      "part": "28.jpg",
      "image": "picsum.photos35.jpg",
      "x": 116,
      "y": 44
    },
    {
      "part": "29.jpg",
      "image": "picsum.photos37.jpg",
      "x": 204,
      "y": 20
    },
    {
      "part": "30.jpg",
      "image": "picsum.photos38.jpg",
      "x": 32,
      "y": 16
    },
    {
      "part": "31.jpg",
      "image": "picsum.photos40.jpg",
      "x": 68,
      "y": 68
    },
    {
      "part": "32.jpg",
      "image": "picsum.photos42.jpg",
      "x": 100,
      "y": 196
    },
    {
      "part": "33.jpg",
      "image": "picsum.photos42.jpg",
      "x": 4,
      "y": 96
    },
    {
      "part": "34.jpg",
      "image": "picsum.photos43.jpg",
      "x": 24,
      "y": 68
    },
    {
      "part": "35.jpg",
      "image": "picsum.photos45.jpg",
      "x": 12,
      "y": 156
    },
    {
      "part": "36.jpg",
      "image": "picsum.photos49.jpg",
      "x": 112,
      "y": 84
    },
    {
      "part": "37.jpg",
      "image": "picsum.photos52.jpg",
      "x": 128,
      "y": 80
    },
    {
      "part": "38.jpg",
      "image": "picsum.photos53.jpg",
      "x": 172,
      "y": 144
    },
    {
      "part": "39.jpg",
      "image": "picsum.photos54.jpg",
      "x": 16,
      "y": 184
    },
    {
      "part": "40.jpg",
      "image": "picsum.photos55.jpg",
      "x": 152,
      "y": 24
    },
    {
      "part": "41.jpg",
      "image": "picsum.photos60.jpg",
      "x": 64,
      "y": 88
    },
    {
      "part": "42.jpg",
      "image": "picsum.photos61.jpg",
      "x": 0,
      "y": 100
    },
    {
      "part": "43.jpg",
      "image": "picsum.photos62.jpg",
      "x": 44,
      "y": 68
    },
    {
      "part": "44.jpg",
      "image": "picsum.photos63.jpg",
      "x": 0,
      "y": 92
    },
    {
      "part": "45.jpg",
      "image": "picsum.photos67.jpg",
      "x": 0,
      "y": 148
    },
    {
      "part": "46.jpg",
      "image": "picsum.photos69.jpg",
      "x": 172,
      "y": 64
    },
    {
      "part": "47.jpg",
      "image": "picsum.photos72.jpg",
      "x": 108,
      "y": 40
    },
    {
      "part": "48.jpg",
      "image": "picsum.photos33.jpg",
      "x": 132,
      "y": 64
    },
    {
      "part": "49.jpg",
      "image": "picsum.photos48.jpg",
      "x": 124,
      "y": 132
    },
    {
      "part": "50.jpg",
      "image": "picsum.photos21.jpg",
      "x": 24,
      "y": 24
    }
  ]
}